{"cameraMode":{"drawMode":0,"name":"Shaded","section":"Shading Mode"},"sceneLighting":true,"audioPlay":false,"sceneViewState":{"showFog":true,"showMaterialUpdate":false,"showSkybox":true,"showFlares":true,"showImageEffects":true,"showParticleSystems":true},"in2DMode":false,"pivot":{"x":18.21295166015625,"y":36.75375747680664,"z":-100.14280700683594},"rotation":{"x":-0.049773238599300387,"y":-0.8110325932502747,"z":0.06977106630802155,"w":-0.57871413230896},"size":178.0731201171875,"orthographic":false}